[
  {
    "title": "Obtainium",
    "description": "Get Android App updates directly from GitHub, GitLab, and more.",
    "url": "https://github.com/ImranRQD/Obtainium",
    "categories": [
      "Android",
      "Apps",
      "Update Manager"
    ],
    "tags": [
      "android",
      "updates",
      "github:black",
      "open-source"
    ],
    "deprecated": false,
    "alternative": null,
    "icon": null
  },
  {
    "title": "myfav",
    "description": "A modular Rust CLI to manage recommendations",
    "url": "https://github.com/pedrobrantes/myfav",
    "categories": [
      "Dev",
      "Tools"
    ],
    "tags": [
      "rust:orange",
      "cli",
      "automation"
    ],
    "deprecated": false,
    "alternative": null,
    "icon": null
  },
  {
    "title": "OpenVideoEditor",
    "description": "Simple and powerful video editor for Android.",
    "url": "https://f-droid.org/packages/io.github.devhyper.openvideoeditor",
    "categories": [
      "Android",
      "Apps",
      "Video Editor"
    ],
    "tags": [
      "android",
      "video-editor",
      "open-source"
    ],
    "deprecated": false,
    "alternative": null,
    "icon": null
  },
  {
    "title": "Stremio",
    "description": "All your video content in one place.",
    "url": "https://www.stremio.com/downloads",
    "categories": [
      "Desktop",
      "Apps",
      "Streaming"
    ],
    "tags": [
      "streaming",
      "movies",
      "series"
    ],
    "deprecated": false,
    "alternative": null,
    "icon": null
  },
  {
    "title": "Xtra",
    "description": "An alternative Twitch frontend for Android.",
    "url": "https://github.com/crackededed/Xtra",
    "categories": [
      "Android",
      "Apps",
      "Streaming"
    ],
    "tags": [
      "android",
      "twitch",
      "streaming",
      "open-source"
    ],
    "deprecated": false,
    "alternative": null,
    "icon": null
  },
  {
    "title": "ImageToolbox",
    "description": "A powerful image manipulation tool for Android.",
    "url": "https://github.com/T8RIN/ImageToolbox",
    "categories": [
      "Android",
      "Apps",
      "Image Editor"
    ],
    "tags": [
      "android",
      "image-editor",
      "utility",
      "open-source"
    ],
    "deprecated": false,
    "alternative": null,
    "icon": null
  },
  {
    "title": "Cherrygram",
    "description": "An alternative, unofficial Telegram client for Android.",
    "url": "https://github.com/arsLan4k1390/Cherrygram",
    "categories": [
      "Android",
      "Apps",
      "Social"
    ],
    "tags": [
      "android",
      "telegram",
      "social",
      "open-source"
    ],
    "deprecated": false,
    "alternative": null,
    "icon": null
  },
  {
    "title": "Mastodon Android",
    "description": "The official Mastodon Android client.",
    "url": "https://github.com/mastodon/mastodon-android",
    "categories": [
      "Android",
      "Apps",
      "Social"
    ],
    "tags": [
      "android",
      "mastodon",
      "social",
      "open-source"
    ],
    "deprecated": false,
    "alternative": null,
    "icon": null
  },
  {
    "title": "Aurora Store",
    "description": "An open-source, unofficial FOSS client for Google Play Store.",
    "url": "https://www.auroraoss.com/AuroraStore/Release",
    "categories": [
      "Android",
      "Apps",
      "Store"
    ],
    "tags": [
      "android",
      "store",
      "open-source"
    ],
    "deprecated": false,
    "alternative": null,
    "icon": null
  },
  {
    "title": "OuterTune",
    "description": "A material-designed music player for Android.",
    "url": "https://github.com/DD3Boh/OuterTune",
    "categories": [
      "Android",
      "Apps",
      "Music Player"
    ],
    "tags": [
      "android",
      "music",
      "player",
      "open-source"
    ],
    "deprecated": false,
    "alternative": null,
    "icon": null
  },
  {
    "title": "LibreTorrent",
    "description": "A lightweight torrent client for Android.",
    "url": "https://f-droid.org/packages/org.proninyaroslav.libretorrent",
    "categories": [
      "Android",
      "Apps",
      "Torrent"
    ],
    "tags": [
      "android",
      "torrent",
      "download",
      "open-source"
    ],
    "deprecated": false,
    "alternative": null,
    "icon": null
  },
  {
    "title": "ReadYou",
    "description": "A simple and elegant RSS reader for Android.",
    "url": "https://github.com/ashinch/readyou",
    "categories": [
      "Android",
      "Apps",
      "RSS"
    ],
    "tags": [
      "android",
      "rss",
      "reader",
      "open-source"
    ],
    "deprecated": false,
    "alternative": null,
    "icon": null
  },
  {
    "title": "AntennaPod",
    "description": "A free and open-source podcast manager and player.",
    "url": "https://f-droid.org/packages/de.danoeh.antennapod",
    "categories": [
      "Android",
      "Apps",
      "Podcasts"
    ],
    "tags": [
      "android",
      "podcast",
      "audio",
      "open-source"
    ],
    "deprecated": false,
    "alternative": null,
    "icon": null
  },
  {
    "title": "PodAura",
    "description": "Modern podcast player built with Jetpack Compose.",
    "url": "https://github.com/SkyD666/PodAura",
    "categories": [
      "Android",
      "Apps",
      "Podcasts"
    ],
    "tags": [
      "android",
      "podcast",
      "material-design",
      "open-source"
    ],
    "deprecated": false,
    "alternative": null,
    "icon": null
  },
  {
    "title": "My Expenses",
    "description": "An open-source, powerful, and intuitive expense manager for Android.",
    "url": "https://f-droid.org/packages/org.totschnig.myexpenses",
    "categories": [
      "Android",
      "Apps",
      "Finance"
    ],
    "tags": [
      "android",
      "finance",
      "expenses",
      "open-source"
    ],
    "deprecated": false,
    "alternative": null,
    "icon": null
  },
  {
    "title": "SummaryExpressive",
    "description": "An Android app for summarizing texts using AI.",
    "url": "https://github.com/kid1412621/SummaryExpressive",
    "categories": [
      "Android",
      "Apps",
      "AI"
    ],
    "tags": [
      "android",
      "ai",
      "summary",
      "open-source"
    ],
    "deprecated": false,
    "alternative": null,
    "icon": null
  },
  {
    "title": "Book Story",
    "description": "A book tracking app for Android.",
    "url": "https://github.com/Acclorite/book-story",
    "categories": [
      "Android",
      "Apps",
      "Books"
    ],
    "tags": [
      "android",
      "books",
      "tracking",
      "open-source"
    ],
    "deprecated": false,
    "alternative": null,
    "icon": null
  },
  {
    "title": "NeverTooManyBooks",
    "description": "Another book management app for Android.",
    "url": "https://github.com/tfonteyn/NeverTooManyBooks",
    "categories": [
      "Android",
      "Apps",
      "Books"
    ],
    "tags": [
      "android",
      "books",
      "tracking",
      "open-source"
    ],
    "deprecated": false,
    "alternative": null,
    "icon": null
  },
  {
    "title": "Readest",
    "description": "A beautiful book tracker for Android.",
    "url": "https://github.com/readest/readest",
    "categories": [
      "Android",
      "Apps",
      "Books"
    ],
    "tags": [
      "android",
      "books",
      "tracking",
      "open-source",
      "material-design"
    ],
    "deprecated": false,
    "alternative": null,
    "icon": null
  },
  {
    "title": "Voice",
    "description": "An audiobook player for Android.",
    "url": "https://github.com/PaulWoitaschek/Voice",
    "categories": [
      "Android",
      "Apps",
      "Audio"
    ],
    "tags": [
      "android",
      "audiobook",
      "player",
      "open-source"
    ],
    "deprecated": false,
    "alternative": null,
    "icon": null
  },
  {
    "title": "MMRL",
    "description": "Magisk Module Repo for LSPosed/Xposed modules.",
    "url": "https://github.com/MMRLApp/MMRL",
    "categories": [
      "Android",
      "Apps",
      "Xposed"
    ],
    "tags": [
      "android",
      "magisk",
      "xposed",
      "modules",
      "open-source"
    ],
    "deprecated": false,
    "alternative": null,
    "icon": null
  },
  {
    "title": "Trail Sense",
    "description": "An all-in-one offline GPS and navigation tool for outdoor activities.",
    "url": "https://github.com/kylecorry31/Trail-Sense",
    "categories": [
      "Android",
      "Apps",
      "Maps"
    ],
    "tags": [
      "android",
      "maps",
      "navigation",
      "outdoor",
      "open-source"
    ],
    "deprecated": false,
    "alternative": null,
    "icon": null
  },
  {
    "title": "CoMaps",
    "description": "A collaborative mapping application based on OpenStreetMap.",
    "url": "https://codeberg.org/comaps/comaps",
    "categories": [
      "Android",
      "Apps",
      "Maps"
    ],
    "tags": [
      "android",
      "maps",
      "osm",
      "collaborative",
      "open-source"
    ],
    "deprecated": false,
    "alternative": null,
    "icon": null
  },
  {
    "title": "AnkiDroid",
    "description": "Anki flashcards for Android.",
    "url": "https://github.com/ankidroid/Anki-Android",
    "categories": [
      "Android",
      "Apps",
      "Study"
    ],
    "tags": [
      "android",
      "study",
      "flashcards",
      "open-source"
    ],
    "deprecated": false,
    "alternative": null,
    "icon": null
  },
  {
    "title": "Atomic Periodic Table",
    "description": "A modern periodic table of elements for Android.",
    "url": "https://github.com/JLindemann42/Atomic-Periodic-Table.Android",
    "categories": [
      "Android",
      "Apps",
      "Study"
    ],
    "tags": [
      "android",
      "study",
      "science",
      "open-source"
    ],
    "deprecated": false,
    "alternative": null,
    "icon": null
  },
  {
    "title": "K-9 Mail",
    "description": "A full-featured open-source email client for Android.",
    "url": "https://f-droid.org/packages/rs.ltt.android",
    "categories": [
      "Android",
      "Apps",
      "Email Client"
    ],
    "tags": [
      "android",
      "email",
      "client",
      "open-source"
    ],
    "deprecated": false,
    "alternative": null,
    "icon": null
  },
  {
    "title": "LibreTube",
    "description": "An alternative frontend for YouTube, for Android.",
    "url": "https://github.com/libre-tube/LibreTube",
    "categories": [
      "Android",
      "Apps",
      "Streaming"
    ],
    "tags": [
      "android",
      "youtube",
      "streaming",
      "open-source"
    ],
    "deprecated": false,
    "alternative": null,
    "icon": null
  },
  {
    "title": "Ciyue",
    "description": "A modern Chinese dictionary for Android.",
    "url": "https://github.com/mumu-lhl/Ciyue",
    "categories": [
      "Android",
      "Apps",
      "Dictionary"
    ],
    "tags": [
      "android",
      "dictionary",
      "chinese",
      "open-source"
    ],
    "deprecated": false,
    "alternative": null,
    "icon": null
  },
  {
    "title": "Rikkahub",
    "description": "An AI-powered app that helps you manage your GitHub projects.",
    "url": "https://github.com/rikkahub/rikkahub",
    "categories": [
      "Android",
      "Apps",
      "AI"
    ],
    "tags": [
      "android",
      "ai",
      "github",
      "productivity",
      "open-source"
    ],
    "deprecated": false,
    "alternative": null,
    "icon": null
  }
]